ternary/__init__.py
beautiful_ternary-1.1.0.dist-info/LICENSE
beautiful_ternary-1.1.0.dist-info/METADATA
beautiful_ternary-1.1.0.dist-info/WHEEL
beautiful_ternary-1.1.0.dist-info/top_level.txt
beautiful_ternary-1.1.0.dist-info/RECORD
