Metadata-Version: 2.1
Name: beautiful-ternary
Version: 1.1.0
Summary: A simple Package to replace the awkward built-in ternary operator with a function call.
Author-email: Christian Witzenberger <christian.witzenberger@triplet.gmbh>
Project-URL: Homepage, https://github.com/redewing/beautiful-ternary
Project-URL: Repository, https://github.com/redewing/beautiful-ternary.git
Project-URL: Issues, https://github.com/redewing/beautiful-ternary/issues
Classifier: Development Status :: 5 - Production/Stable
Classifier: Programming Language :: Python :: 3
Classifier: License :: OSI Approved :: MIT License
Classifier: Operating System :: OS Independent
Requires-Python: >=3.8
License-File: LICENSE
